{
	"users": [
		{
			"name": "Dale Jacobi",
			"age": 45,
			"position": "Director",
			"gender": "Male",
			"id": "6ae69707-cdb4-4b4a-94bc-8d1d45fe250c"
		},
		{
			"name": "Gwen Green",
			"age": 38,
			"position": "Specialist",
			"gender": "Female",
			"id": "c662afce-9be2-445f-ad57-8df029d7d78c"
		},
		{
			"name": "Felicia Cummings",
			"age": 43,
			"position": "Coordinator",
			"gender": "Female",
			"id": "24fdfb30-f6a6-4a75-87af-b51d91f4e10c"
		},
		{
			"name": "Lue Carroll",
			"age": 49,
			"position": "Technician",
			"gender": "Male",
			"id": "6eb4146e-5d3c-4ab9-a0e3-a5fdb6252eed"
		},
		{
			"name": "Randal Corwin",
			"age": 32,
			"position": "Specialist",
			"gender": "Male",
			"id": "8a46acec-0146-4e53-b2c8-932bb08d5098"
		},
		{
			"name": "Javier Gorczany",
			"age": 57,
			"position": "Specialist",
			"gender": "Female",
			"id": "5e64d2cc-f254-4fa4-8fd1-c1066ef5616d"
		},
		{
			"name": "Claire Runte",
			"age": 56,
			"position": "Director",
			"gender": "Female",
			"id": "04e34d3e-bd97-4e05-bd7e-eed28c5829e8"
		},
		{
			"name": "Ricardo Fadel",
			"age": 21,
			"position": "Consultant",
			"gender": "Male",
			"id": "650010ed-95a0-4731-b5ce-f0a66737d76d"
		},
		{
			"name": "Julius Baumbach",
			"age": 41,
			"position": "Designer",
			"gender": "Female",
			"id": "7b3d6eb8-f1a6-4fb8-a230-73b9e243cdef"
		},
		{
			"name": "Gail Koelpin",
			"age": 35,
			"position": "Agent",
			"gender": "Male",
			"id": "d6a9bee5-9a54-4d55-8b46-fd13ad084acd"
		},
		{
			"name": "Winston Herzog",
			"age": 42,
			"position": "Technician",
			"gender": "Male",
			"id": "42bbb71a-db68-4920-bc85-58efb75b4a6f"
		},
		{
			"name": "Miss Darlene Huel",
			"age": 32,
			"position": "Technician",
			"gender": "Female",
			"id": "87678002-50cc-4809-b6a9-0ad9b276c366"
		},
		{
			"name": "Luz Turner",
			"age": 46,
			"position": "Officer",
			"gender": "Female",
			"id": "f69fee96-48d8-4e6a-8e2b-4a0dedf7da39"
		},
		{
			"name": "Gwen Effertz DDS",
			"age": 38,
			"position": "Specialist",
			"gender": "Female",
			"id": "c662afce-9be2-445f-ad57-8df029d7d78c"
		},
		{
			"name": "Felicia Cummings",
			"age": 43,
			"position": "Coordinator",
			"gender": "Female",
			"id": "24fdfb30-f6a6-4a75-87af-b51d91f4e10c"
		},
		{
			"name": "Lue Carroll",
			"age": 49,
			"position": "Technician",
			"gender": "Male",
			"id": "6eb4146e-5d3c-4ab9-a0e3-a5fdb6252eed"
		},
		{
			"name": "Randal Corwin",
			"age": 32,
			"position": "Specialist",
			"gender": "Male",
			"id": "8a46acec-0146-4e53-b2c8-932bb08d5098"
		},
		{
			"name": "Javier Gorczany",
			"age": 57,
			"position": "Specialist",
			"gender": "Female",
			"id": "5e64d2cc-f254-4fa4-8fd1-c1066ef5616d"
		},
		{
			"name": "Claire Runte",
			"age": 56,
			"position": "Director",
			"gender": "Female",
			"id": "04e34d3e-bd97-4e05-bd7e-eed28c5829e8"
		},
		{
			"name": "Ricardo Fadel",
			"age": 21,
			"position": "Consultant",
			"gender": "Male",
			"id": "650010ed-95a0-4731-b5ce-f0a66737d76d"
		},
		{
			"name": "Julius Baumbach",
			"age": 41,
			"position": "Designer",
			"gender": "Female",
			"id": "7b3d6eb8-f1a6-4fb8-a230-73b9e243cdef"
		},
		{
			"name": "Gail Koelpin",
			"age": 35,
			"position": "Agent",
			"gender": "Male",
			"id": "d6a9bee5-9a54-4d55-8b46-fd13ad084acd"
		},
		{
			"name": "Winston Herzog",
			"age": 42,
			"position": "Technician",
			"gender": "Male",
			"id": "42bbb71a-db68-4920-bc85-58efb75b4a6f"
		},
		{
			"name": "Miss Darlene Huel",
			"age": 32,
			"position": "Technician",
			"gender": "Female",
			"id": "87678002-50cc-4809-b6a9-0ad9b276c366"
		},
		{
			"name": "Luz Turner",
			"age": 46,
			"position": "Officer",
			"gender": "Female",
			"id": "f69fee96-48d8-4e6a-8e2b-4a0dedf7da39"
		},
		{
			"name": "Antoinette Ferry",
			"age": 56,
			"position": "Orchestrator",
			"gender": "Female",
			"id": "64cb64b9-532a-4e75-a8b8-4423403cb3e6"
		}
	]
}
